{
    "os": "Linux-5.4.0-125-generic-x86_64-with-glibc2.17",
    "python": "3.8.10",
    "heartbeatAt": "2023-03-17T00:03:24.898598",
    "startedAt": "2023-03-17T00:03:22.742306",
    "docker": null,
    "cuda": null,
    "args": [],
    "state": "running",
    "program": "train.py",
    "codePath": "train.py",
    "host": "autodl-container-912d11a43c-d687a7f6",
    "username": "root",
    "executable": "/root/miniconda3/bin/python",
    "cpu_count": 64,
    "cpu_count_logical": 128,
    "cpu_freq": {
        "current": 901.8585859375003,
        "min": 800.0,
        "max": 3500.0
    },
    "cpu_freq_per_core": [
        {
            "current": 937.111,
            "min": 800.0,
            "max": 3500.0
        },
        {
            "current": 800.082,
            "min": 800.0,
            "max": 3500.0
        },
        {
            "current": 891.055,
            "min": 800.0,
            "max": 3500.0
        },
        {
            "current": 800.359,
            "min": 800.0,
            "max": 3500.0
        },
        {
            "current": 801.115,
            "min": 800.0,
            "max": 3500.0
        },
        {
            "current": 800.064,
            "min": 800.0,
            "max": 3500.0
        },
        {
            "current": 861.751,
            "min": 800.0,
            "max": 3500.0
        },
        {
            "current": 800.762,
            "min": 800.0,
            "max": 3500.0
        },
        {
            "current": 800.782,
            "min": 800.0,
            "max": 3500.0
        },
        {
            "current": 800.337,
            "min": 800.0,
            "max": 3500.0
        },
        {
            "current": 800.759,
            "min": 800.0,
            "max": 3500.0
        },
        {
            "current": 919.546,
            "min": 800.0,
            "max": 3500.0
        },
        {
            "current": 800.729,
            "min": 800.0,
            "max": 3500.0
        },
        {
            "current": 801.131,
            "min": 800.0,
            "max": 3500.0
        },
        {
            "current": 800.104,
            "min": 800.0,
            "max": 3500.0
        },
        {
            "current": 801.17,
            "min": 800.0,
            "max": 3500.0
        },
        {
            "current": 801.158,
            "min": 800.0,
            "max": 3500.0
        },
        {
            "current": 800.166,
            "min": 800.0,
            "max": 3500.0
        },
        {
            "current": 800.375,
            "min": 800.0,
            "max": 3500.0
        },
        {
            "current": 800.091,
            "min": 800.0,
            "max": 3500.0
        },
        {
            "current": 800.27,
            "min": 800.0,
            "max": 3500.0
        },
        {
            "current": 892.277,
            "min": 800.0,
            "max": 3500.0
        },
        {
            "current": 800.791,
            "min": 800.0,
            "max": 3500.0
        },
        {
            "current": 801.82,
            "min": 800.0,
            "max": 3500.0
        },
        {
            "current": 800.768,
            "min": 800.0,
            "max": 3500.0
        },
        {
            "current": 895.184,
            "min": 800.0,
            "max": 3500.0
        },
        {
            "current": 800.107,
            "min": 800.0,
            "max": 3500.0
        },
        {
            "current": 863.214,
            "min": 800.0,
            "max": 3500.0
        },
        {
            "current": 880.134,
            "min": 800.0,
            "max": 3500.0
        },
        {
            "current": 800.841,
            "min": 800.0,
            "max": 3500.0
        },
        {
            "current": 800.5,
            "min": 800.0,
            "max": 3500.0
        },
        {
            "current": 853.096,
            "min": 800.0,
            "max": 3500.0
        },
        {
            "current": 801.102,
            "min": 800.0,
            "max": 3500.0
        },
        {
            "current": 800.323,
            "min": 800.0,
            "max": 3500.0
        },
        {
            "current": 801.149,
            "min": 800.0,
            "max": 3500.0
        },
        {
            "current": 801.074,
            "min": 800.0,
            "max": 3500.0
        },
        {
            "current": 858.311,
            "min": 800.0,
            "max": 3500.0
        },
        {
            "current": 800.156,
            "min": 800.0,
            "max": 3500.0
        },
        {
            "current": 800.37,
            "min": 800.0,
            "max": 3500.0
        },
        {
            "current": 800.77,
            "min": 800.0,
            "max": 3500.0
        },
        {
            "current": 2600.0,
            "min": 800.0,
            "max": 3500.0
        },
        {
            "current": 906.679,
            "min": 800.0,
            "max": 3500.0
        },
        {
            "current": 801.094,
            "min": 800.0,
            "max": 3500.0
        },
        {
            "current": 801.131,
            "min": 800.0,
            "max": 3500.0
        },
        {
            "current": 801.102,
            "min": 800.0,
            "max": 3500.0
        },
        {
            "current": 800.359,
            "min": 800.0,
            "max": 3500.0
        },
        {
            "current": 800.777,
            "min": 800.0,
            "max": 3500.0
        },
        {
            "current": 800.761,
            "min": 800.0,
            "max": 3500.0
        },
        {
            "current": 800.762,
            "min": 800.0,
            "max": 3500.0
        },
        {
            "current": 800.268,
            "min": 800.0,
            "max": 3500.0
        },
        {
            "current": 800.775,
            "min": 800.0,
            "max": 3500.0
        },
        {
            "current": 801.151,
            "min": 800.0,
            "max": 3500.0
        },
        {
            "current": 862.799,
            "min": 800.0,
            "max": 3500.0
        },
        {
            "current": 801.191,
            "min": 800.0,
            "max": 3500.0
        },
        {
            "current": 801.167,
            "min": 800.0,
            "max": 3500.0
        },
        {
            "current": 800.791,
            "min": 800.0,
            "max": 3500.0
        },
        {
            "current": 801.577,
            "min": 800.0,
            "max": 3500.0
        },
        {
            "current": 808.409,
            "min": 800.0,
            "max": 3500.0
        },
        {
            "current": 819.79,
            "min": 800.0,
            "max": 3500.0
        },
        {
            "current": 800.768,
            "min": 800.0,
            "max": 3500.0
        },
        {
            "current": 801.164,
            "min": 800.0,
            "max": 3500.0
        },
        {
            "current": 801.546,
            "min": 800.0,
            "max": 3500.0
        },
        {
            "current": 801.158,
            "min": 800.0,
            "max": 3500.0
        },
        {
            "current": 801.114,
            "min": 800.0,
            "max": 3500.0
        },
        {
            "current": 815.678,
            "min": 800.0,
            "max": 3500.0
        },
        {
            "current": 801.132,
            "min": 800.0,
            "max": 3500.0
        },
        {
            "current": 789.832,
            "min": 800.0,
            "max": 3500.0
        },
        {
            "current": 801.098,
            "min": 800.0,
            "max": 3500.0
        },
        {
            "current": 801.104,
            "min": 800.0,
            "max": 3500.0
        },
        {
            "current": 801.162,
            "min": 800.0,
            "max": 3500.0
        },
        {
            "current": 855.158,
            "min": 800.0,
            "max": 3500.0
        },
        {
            "current": 923.374,
            "min": 800.0,
            "max": 3500.0
        },
        {
            "current": 800.784,
            "min": 800.0,
            "max": 3500.0
        },
        {
            "current": 800.229,
            "min": 800.0,
            "max": 3500.0
        },
        {
            "current": 801.54,
            "min": 800.0,
            "max": 3500.0
        },
        {
            "current": 800.796,
            "min": 800.0,
            "max": 3500.0
        },
        {
            "current": 801.028,
            "min": 800.0,
            "max": 3500.0
        },
        {
            "current": 800.147,
            "min": 800.0,
            "max": 3500.0
        },
        {
            "current": 800.8,
            "min": 800.0,
            "max": 3500.0
        },
        {
            "current": 815.207,
            "min": 800.0,
            "max": 3500.0
        },
        {
            "current": 800.292,
            "min": 800.0,
            "max": 3500.0
        },
        {
            "current": 800.773,
            "min": 800.0,
            "max": 3500.0
        },
        {
            "current": 801.147,
            "min": 800.0,
            "max": 3500.0
        },
        {
            "current": 801.172,
            "min": 800.0,
            "max": 3500.0
        },
        {
            "current": 800.787,
            "min": 800.0,
            "max": 3500.0
        },
        {
            "current": 899.409,
            "min": 800.0,
            "max": 3500.0
        },
        {
            "current": 856.025,
            "min": 800.0,
            "max": 3500.0
        },
        {
            "current": 889.65,
            "min": 800.0,
            "max": 3500.0
        },
        {
            "current": 800.813,
            "min": 800.0,
            "max": 3500.0
        },
        {
            "current": 866.253,
            "min": 800.0,
            "max": 3500.0
        },
        {
            "current": 800.142,
            "min": 800.0,
            "max": 3500.0
        },
        {
            "current": 896.423,
            "min": 800.0,
            "max": 3500.0
        },
        {
            "current": 788.452,
            "min": 800.0,
            "max": 3500.0
        },
        {
            "current": 849.669,
            "min": 800.0,
            "max": 3500.0
        },
        {
            "current": 801.163,
            "min": 800.0,
            "max": 3500.0
        },
        {
            "current": 800.382,
            "min": 800.0,
            "max": 3500.0
        },
        {
            "current": 800.171,
            "min": 800.0,
            "max": 3500.0
        },
        {
            "current": 800.771,
            "min": 800.0,
            "max": 3500.0
        },
        {
            "current": 800.779,
            "min": 800.0,
            "max": 3500.0
        },
        {
            "current": 1400.828,
            "min": 800.0,
            "max": 3500.0
        },
        {
            "current": 811.625,
            "min": 800.0,
            "max": 3500.0
        },
        {
            "current": 800.79,
            "min": 800.0,
            "max": 3500.0
        },
        {
            "current": 838.66,
            "min": 800.0,
            "max": 3500.0
        },
        {
            "current": 801.151,
            "min": 800.0,
            "max": 3500.0
        },
        {
            "current": 2596.886,
            "min": 800.0,
            "max": 3500.0
        },
        {
            "current": 800.369,
            "min": 800.0,
            "max": 3500.0
        },
        {
            "current": 800.755,
            "min": 800.0,
            "max": 3500.0
        },
        {
            "current": 801.181,
            "min": 800.0,
            "max": 3500.0
        },
        {
            "current": 801.522,
            "min": 800.0,
            "max": 3500.0
        },
        {
            "current": 800.702,
            "min": 800.0,
            "max": 3500.0
        },
        {
            "current": 801.156,
            "min": 800.0,
            "max": 3500.0
        },
        {
            "current": 800.38,
            "min": 800.0,
            "max": 3500.0
        },
        {
            "current": 800.377,
            "min": 800.0,
            "max": 3500.0
        },
        {
            "current": 801.151,
            "min": 800.0,
            "max": 3500.0
        },
        {
            "current": 800.208,
            "min": 800.0,
            "max": 3500.0
        },
        {
            "current": 800.774,
            "min": 800.0,
            "max": 3500.0
        },
        {
            "current": 876.015,
            "min": 800.0,
            "max": 3500.0
        },
        {
            "current": 800.816,
            "min": 800.0,
            "max": 3500.0
        },
        {
            "current": 801.204,
            "min": 800.0,
            "max": 3500.0
        },
        {
            "current": 801.608,
            "min": 800.0,
            "max": 3500.0
        },
        {
            "current": 904.125,
            "min": 800.0,
            "max": 3500.0
        },
        {
            "current": 801.198,
            "min": 800.0,
            "max": 3500.0
        },
        {
            "current": 811.227,
            "min": 800.0,
            "max": 3500.0
        },
        {
            "current": 1801.319,
            "min": 800.0,
            "max": 3500.0
        },
        {
            "current": 800.796,
            "min": 800.0,
            "max": 3500.0
        },
        {
            "current": 1101.287,
            "min": 800.0,
            "max": 3500.0
        },
        {
            "current": 800.785,
            "min": 800.0,
            "max": 3500.0
        },
        {
            "current": 801.479,
            "min": 800.0,
            "max": 3500.0
        }
    ],
    "disk": {
        "total": 25.0,
        "used": 9.533607482910156
    },
    "gpu": "NVIDIA GeForce RTX 3080 Ti",
    "gpu_count": 1,
    "gpu_devices": [
        {
            "name": "NVIDIA GeForce RTX 3080 Ti",
            "memory_total": 12884901888
        }
    ],
    "memory": {
        "total": 377.5375099182129
    }
}
