{
    "os": "Linux-5.4.0-125-generic-x86_64-with-glibc2.17",
    "python": "3.8.10",
    "heartbeatAt": "2023-03-19T10:30:39.720399",
    "startedAt": "2023-03-19T10:30:35.657158",
    "docker": null,
    "cuda": null,
    "args": [],
    "state": "running",
    "program": "train.py",
    "codePath": "train.py",
    "host": "autodl-container-912d11a43c-d687a7f6",
    "username": "root",
    "executable": "/root/miniconda3/bin/python",
    "cpu_count": 64,
    "cpu_count_logical": 128,
    "cpu_freq": {
        "current": 1407.1485000000007,
        "min": 800.0,
        "max": 3500.0
    },
    "cpu_freq_per_core": [
        {
            "current": 1100.721,
            "min": 800.0,
            "max": 3500.0
        },
        {
            "current": 800.753,
            "min": 800.0,
            "max": 3500.0
        },
        {
            "current": 800.0,
            "min": 800.0,
            "max": 3500.0
        },
        {
            "current": 1789.229,
            "min": 800.0,
            "max": 3500.0
        },
        {
            "current": 800.046,
            "min": 800.0,
            "max": 3500.0
        },
        {
            "current": 1400.0,
            "min": 800.0,
            "max": 3500.0
        },
        {
            "current": 800.521,
            "min": 800.0,
            "max": 3500.0
        },
        {
            "current": 900.0,
            "min": 800.0,
            "max": 3500.0
        },
        {
            "current": 900.0,
            "min": 800.0,
            "max": 3500.0
        },
        {
            "current": 1020.55,
            "min": 800.0,
            "max": 3500.0
        },
        {
            "current": 863.616,
            "min": 800.0,
            "max": 3500.0
        },
        {
            "current": 1842.346,
            "min": 800.0,
            "max": 3500.0
        },
        {
            "current": 1598.476,
            "min": 800.0,
            "max": 3500.0
        },
        {
            "current": 913.907,
            "min": 800.0,
            "max": 3500.0
        },
        {
            "current": 865.297,
            "min": 800.0,
            "max": 3500.0
        },
        {
            "current": 826.388,
            "min": 800.0,
            "max": 3500.0
        },
        {
            "current": 800.825,
            "min": 800.0,
            "max": 3500.0
        },
        {
            "current": 800.504,
            "min": 800.0,
            "max": 3500.0
        },
        {
            "current": 836.696,
            "min": 800.0,
            "max": 3500.0
        },
        {
            "current": 900.0,
            "min": 800.0,
            "max": 3500.0
        },
        {
            "current": 893.024,
            "min": 800.0,
            "max": 3500.0
        },
        {
            "current": 800.539,
            "min": 800.0,
            "max": 3500.0
        },
        {
            "current": 897.109,
            "min": 800.0,
            "max": 3500.0
        },
        {
            "current": 800.0,
            "min": 800.0,
            "max": 3500.0
        },
        {
            "current": 799.321,
            "min": 800.0,
            "max": 3500.0
        },
        {
            "current": 3204.023,
            "min": 800.0,
            "max": 3500.0
        },
        {
            "current": 3100.0,
            "min": 800.0,
            "max": 3500.0
        },
        {
            "current": 800.047,
            "min": 800.0,
            "max": 3500.0
        },
        {
            "current": 874.278,
            "min": 800.0,
            "max": 3500.0
        },
        {
            "current": 800.117,
            "min": 800.0,
            "max": 3500.0
        },
        {
            "current": 837.817,
            "min": 800.0,
            "max": 3500.0
        },
        {
            "current": 3096.237,
            "min": 800.0,
            "max": 3500.0
        },
        {
            "current": 2602.355,
            "min": 800.0,
            "max": 3500.0
        },
        {
            "current": 1100.0,
            "min": 800.0,
            "max": 3500.0
        },
        {
            "current": 831.741,
            "min": 800.0,
            "max": 3500.0
        },
        {
            "current": 1011.115,
            "min": 800.0,
            "max": 3500.0
        },
        {
            "current": 800.543,
            "min": 800.0,
            "max": 3500.0
        },
        {
            "current": 800.715,
            "min": 800.0,
            "max": 3500.0
        },
        {
            "current": 3198.901,
            "min": 800.0,
            "max": 3500.0
        },
        {
            "current": 800.823,
            "min": 800.0,
            "max": 3500.0
        },
        {
            "current": 1370.499,
            "min": 800.0,
            "max": 3500.0
        },
        {
            "current": 800.252,
            "min": 800.0,
            "max": 3500.0
        },
        {
            "current": 800.625,
            "min": 800.0,
            "max": 3500.0
        },
        {
            "current": 2490.118,
            "min": 800.0,
            "max": 3500.0
        },
        {
            "current": 1003.593,
            "min": 800.0,
            "max": 3500.0
        },
        {
            "current": 800.726,
            "min": 800.0,
            "max": 3500.0
        },
        {
            "current": 3204.019,
            "min": 800.0,
            "max": 3500.0
        },
        {
            "current": 897.388,
            "min": 800.0,
            "max": 3500.0
        },
        {
            "current": 895.453,
            "min": 800.0,
            "max": 3500.0
        },
        {
            "current": 841.222,
            "min": 800.0,
            "max": 3500.0
        },
        {
            "current": 1722.432,
            "min": 800.0,
            "max": 3500.0
        },
        {
            "current": 3184.409,
            "min": 800.0,
            "max": 3500.0
        },
        {
            "current": 857.571,
            "min": 800.0,
            "max": 3500.0
        },
        {
            "current": 1143.575,
            "min": 800.0,
            "max": 3500.0
        },
        {
            "current": 800.06,
            "min": 800.0,
            "max": 3500.0
        },
        {
            "current": 2201.568,
            "min": 800.0,
            "max": 3500.0
        },
        {
            "current": 3200.0,
            "min": 800.0,
            "max": 3500.0
        },
        {
            "current": 849.23,
            "min": 800.0,
            "max": 3500.0
        },
        {
            "current": 882.2,
            "min": 800.0,
            "max": 3500.0
        },
        {
            "current": 943.829,
            "min": 800.0,
            "max": 3500.0
        },
        {
            "current": 3185.615,
            "min": 800.0,
            "max": 3500.0
        },
        {
            "current": 799.98,
            "min": 800.0,
            "max": 3500.0
        },
        {
            "current": 831.479,
            "min": 800.0,
            "max": 3500.0
        },
        {
            "current": 800.764,
            "min": 800.0,
            "max": 3500.0
        },
        {
            "current": 982.578,
            "min": 800.0,
            "max": 3500.0
        },
        {
            "current": 801.108,
            "min": 800.0,
            "max": 3500.0
        },
        {
            "current": 800.0,
            "min": 800.0,
            "max": 3500.0
        },
        {
            "current": 989.606,
            "min": 800.0,
            "max": 3500.0
        },
        {
            "current": 800.928,
            "min": 800.0,
            "max": 3500.0
        },
        {
            "current": 1400.903,
            "min": 800.0,
            "max": 3500.0
        },
        {
            "current": 800.748,
            "min": 800.0,
            "max": 3500.0
        },
        {
            "current": 888.722,
            "min": 800.0,
            "max": 3500.0
        },
        {
            "current": 900.0,
            "min": 800.0,
            "max": 3500.0
        },
        {
            "current": 1250.204,
            "min": 800.0,
            "max": 3500.0
        },
        {
            "current": 800.0,
            "min": 800.0,
            "max": 3500.0
        },
        {
            "current": 1960.762,
            "min": 800.0,
            "max": 3500.0
        },
        {
            "current": 1512.354,
            "min": 800.0,
            "max": 3500.0
        },
        {
            "current": 800.0,
            "min": 800.0,
            "max": 3500.0
        },
        {
            "current": 900.847,
            "min": 800.0,
            "max": 3500.0
        },
        {
            "current": 800.708,
            "min": 800.0,
            "max": 3500.0
        },
        {
            "current": 800.446,
            "min": 800.0,
            "max": 3500.0
        },
        {
            "current": 800.745,
            "min": 800.0,
            "max": 3500.0
        },
        {
            "current": 800.0,
            "min": 800.0,
            "max": 3500.0
        },
        {
            "current": 899.273,
            "min": 800.0,
            "max": 3500.0
        },
        {
            "current": 900.0,
            "min": 800.0,
            "max": 3500.0
        },
        {
            "current": 800.617,
            "min": 800.0,
            "max": 3500.0
        },
        {
            "current": 898.893,
            "min": 800.0,
            "max": 3500.0
        },
        {
            "current": 800.0,
            "min": 800.0,
            "max": 3500.0
        },
        {
            "current": 800.0,
            "min": 800.0,
            "max": 3500.0
        },
        {
            "current": 3159.034,
            "min": 800.0,
            "max": 3500.0
        },
        {
            "current": 3163.295,
            "min": 800.0,
            "max": 3500.0
        },
        {
            "current": 800.144,
            "min": 800.0,
            "max": 3500.0
        },
        {
            "current": 835.781,
            "min": 800.0,
            "max": 3500.0
        },
        {
            "current": 800.076,
            "min": 800.0,
            "max": 3500.0
        },
        {
            "current": 994.879,
            "min": 800.0,
            "max": 3500.0
        },
        {
            "current": 3163.311,
            "min": 800.0,
            "max": 3500.0
        },
        {
            "current": 2600.0,
            "min": 800.0,
            "max": 3500.0
        },
        {
            "current": 1100.0,
            "min": 800.0,
            "max": 3500.0
        },
        {
            "current": 866.341,
            "min": 800.0,
            "max": 3500.0
        },
        {
            "current": 890.65,
            "min": 800.0,
            "max": 3500.0
        },
        {
            "current": 800.18,
            "min": 800.0,
            "max": 3500.0
        },
        {
            "current": 1501.001,
            "min": 800.0,
            "max": 3500.0
        },
        {
            "current": 3138.173,
            "min": 800.0,
            "max": 3500.0
        },
        {
            "current": 800.112,
            "min": 800.0,
            "max": 3500.0
        },
        {
            "current": 1846.726,
            "min": 800.0,
            "max": 3500.0
        },
        {
            "current": 801.185,
            "min": 800.0,
            "max": 3500.0
        },
        {
            "current": 801.107,
            "min": 800.0,
            "max": 3500.0
        },
        {
            "current": 2149.909,
            "min": 800.0,
            "max": 3500.0
        },
        {
            "current": 1078.059,
            "min": 800.0,
            "max": 3500.0
        },
        {
            "current": 800.344,
            "min": 800.0,
            "max": 3500.0
        },
        {
            "current": 3141.686,
            "min": 800.0,
            "max": 3500.0
        },
        {
            "current": 897.342,
            "min": 800.0,
            "max": 3500.0
        },
        {
            "current": 1733.25,
            "min": 800.0,
            "max": 3500.0
        },
        {
            "current": 858.631,
            "min": 800.0,
            "max": 3500.0
        },
        {
            "current": 1278.185,
            "min": 800.0,
            "max": 3500.0
        },
        {
            "current": 3100.0,
            "min": 800.0,
            "max": 3500.0
        },
        {
            "current": 867.491,
            "min": 800.0,
            "max": 3500.0
        },
        {
            "current": 899.981,
            "min": 800.0,
            "max": 3500.0
        },
        {
            "current": 800.669,
            "min": 800.0,
            "max": 3500.0
        },
        {
            "current": 1342.936,
            "min": 800.0,
            "max": 3500.0
        },
        {
            "current": 3215.166,
            "min": 800.0,
            "max": 3500.0
        },
        {
            "current": 858.177,
            "min": 800.0,
            "max": 3500.0
        },
        {
            "current": 830.841,
            "min": 800.0,
            "max": 3500.0
        },
        {
            "current": 800.99,
            "min": 800.0,
            "max": 3500.0
        },
        {
            "current": 3203.31,
            "min": 800.0,
            "max": 3500.0
        },
        {
            "current": 799.074,
            "min": 800.0,
            "max": 3500.0
        },
        {
            "current": 836.382,
            "min": 800.0,
            "max": 3500.0
        },
        {
            "current": 801.594,
            "min": 800.0,
            "max": 3500.0
        }
    ],
    "disk": {
        "total": 25.0,
        "used": 9.500946044921875
    },
    "gpu": "NVIDIA GeForce RTX 3080 Ti",
    "gpu_count": 1,
    "gpu_devices": [
        {
            "name": "NVIDIA GeForce RTX 3080 Ti",
            "memory_total": 12884901888
        }
    ],
    "memory": {
        "total": 377.5375099182129
    }
}
